pyotm/JavaConnect.py
pyotm/OTMWrapper.py
pyotm/__init__.py
pyotm/otm-sim-1.0-SNAPSHOT-jar-with-dependencies.jar
pyotm/test_advance.py
pyotm/test_run.py
pyotm-0.0.3.dist-info/LICENSE
pyotm-0.0.3.dist-info/METADATA
pyotm-0.0.3.dist-info/WHEEL
pyotm-0.0.3.dist-info/top_level.txt
pyotm-0.0.3.dist-info/RECORD
