Metadata-Version: 2.1
Name: pyotm
Version: 0.0.3
Summary: Python connector for OTM
Author-email: Gabriel Gomes <gomes@berkeley.edu>
Project-URL: homepage, https://github.com/ggomes/otm-sim
Classifier: Programming Language :: Python :: 3
Classifier: License :: OSI Approved :: MIT License
Classifier: Operating System :: OS Independent
Requires-Python: >=3.7
License-File: LICENSE
Requires-Dist: py4j
Requires-Dist: numpy
